{
  "generatedAt": "2026-06-23T09:33:21.607Z",
  "lookbackHours": 336,
  "podcasts": [
    {
      "source": "podcast",
      "name": "Bankless",
      "title": "NEAR’s AI Money Thesis: Intents, Privacy, and Tokenomics | Sal Ternullo",
      "guid": "flightcast:01KSMCYDT2WJDH9YFCCNA07PDN",
      "url": "https://www.youtube.com/@Bankless",
      "podcastUrl": "https://www.youtube.com/@Bankless",
      "publishedAt": "2026-05-27T10:30:00.000Z",
      "description": "NEAR keeps showing up in strange places: cross-chain wallets, privacy apps, AI infrastructure, and now the emerging agent economy. Sal Ternullo, CEO of SVRN, joins us to explain why he thinks this is not another NEAR pivot, but the original thesis finally coming into focus. They dig into NEAR Intents, AI money, tokenomics, privacy, fee capture, agentic commerce, and why SVRN is trying to commercialize the NEAR ecosystem rather than simply hold the asset. --- 🧭OKX | 120M+ USERS WORLDWIDE https://bankless.cc/OKXapp --- BANKLESS SPONSOR TOOLS: 🔮POLYMARKET | #1 PREDICTION MARKET https://bankless.cc/polymarket-podcast 🟦 COINBASE ONE | MEMBER MONTH https://bankless.cc/coinbase-one 🧭OKX | TRADE, EARN, PAY to OKX | 120M+ USERS WORLDWIDE https://app.okx.com/join/USBANKLESS 🦊 METAMASK | DOWNLOAD NOW https://go.metamask.io/BL-Pod-Download 🌐BRIX | EMERGING MARKET YIELD https://bankless.cc/brix 🎯THE DEFI REPORT | ONCHAIN INSIGHTS https://thedefireport.io/bankless --- TIMESTAMPS 0:00 Intro 2:23 Why NEAR Keeps Showing Up 3:58 Pivot or Return to Roots? 7:41 The “AI Money” Thesis 9:54 Intents, Zashi, and Real Product Market Fit 11:38 Tokenomics, Buybacks, and Value Accrual 14:45 NEAR’s Different Approach From Ethereum 18:00 Fees, Scaling, and First-Party Apps 23:04 Cross-Chain Liquidity as NEAR’s Moat 28:27 The Contrarian Investor Case for NEAR 31:43 Privacy, Enterprises, and AI Agents 39:38 What SVRN Is Building for NEAR 46:00 Investor Sentiment and Final Thoughts --- RESOURCES Sal Ternullo https://x.com/sal_ternullo SVRN https://x.com/svrn_ai --- Not financial or tax advice. See our investment disclosures here: https://www.bankless.com/disclosures"
    },
    {
      "source": "podcast",
      "name": "Tokenized",
      "title": "SpaceX IPO Broke Tokenized Stocks",
      "guid": "e3a58642-2449-47d7-bd89-8ff00a41837b",
      "url": "https://tokenized.simplecast.com/episodes/spaces-ipo-broke-tokenized-stocks-GVEC0sT3",
      "podcastUrl": "https://www.youtube.com/@TokenizedPodcast",
      "publishedAt": "2026-06-22T15:00:00.000Z",
      "description": "On Ep. 88 of Tokenized, Simon Taylor, Head of Market Development @ Tempo and Cuy Sheffield, Head of Crypto @ Visa, are joined by Eli Cohen, Chief Legal Officer @ Centrifuge and Ross Basri, Co-Founder @ Uptop (acq by Rain) to discuss Zelle launching ZelleUSD, banks using stablecoins for cross border payments and more! Timestamps: 00:00 Introduction 2:26 Zelle launching ZelleUSD stablecoin and India expansion 3:48 Banks using stablecoins for cross border payments 5:45 Zelle competing with Revolut and Wise internationally 8:59 Banks embedding FX services into stablecoin products 11:28 Rain launches native loyalty for stablecoin card programs 17:54 Using yield from stablecoins to fund card rewards 24:50 Rain offers credit cards and on chain rewards modules 27:50 Crypto exchanges cancel SpaceX pre IPO token orders 37:51 Different legal models for tokenized securities explained Tokenized is sponsored by Visa A world leader in digital payments, Visa is bridging the gap between traditional financial institutions and innovative blockchain networks, helping players in the payments ecosystem navigate the ever-evolving world of tokenized fiat currencies with confidence and ease. Learn more at visa.com/crypto . Tokenized is presented by Bridge, a Stripe company. Just like the internet made information global, stablecoins are making money global. And Bridge, a Stripe company, is the infrastructure powering that shift. Built for speed, scale, and simplicity, Bridge helps businesses send, store, convert, and spend stablecoins instantly, all without borders or having to navigate the complexities of crypto. Learn more at bridge.xyz Tokenized is presented by M0 Stablecoins are becoming global financial infrastructure. It's time for that infrastructure to mature. If you're a brand, you should have your own stablecoin set to the behavior of financial flows moving through your product. If you're an issuer, you want to be the stablecoin partner for the most valuable brands. M0 is the only platform where issuers and brands get together to build digital money products for the world. Learn more at m0.org *** We’d also like to remind you that the views or opinions of our contributors today are their own and do not necessarily reflect those of the companies they are representing. Nothing we say should be taken as tax, financial, investment or legal advice, do your own research! Music by Henry McLean"
    },
    {
      "source": "podcast",
      "name": "Tech Snippets Today with Joseph Raczynski",
      "title": "Behind Closed Doors: Why Wall Street is Building on ZKsync with Matter Labs CEO Alex Gluchowski",
      "guid": "Buzzsprout-19339802",
      "url": "https://www.youtube.com/@JosephRaczynski",
      "podcastUrl": "https://www.youtube.com/@JosephRaczynski",
      "publishedAt": "2026-06-22T13:00:00.000Z",
      "description": "Today, we are recording live from ETHConf in New York City, and I am sitting down with Alex Gluchowski, CEO and co-founder of Matter Labs—the driving force behind the massively backed ZKsync ecosystem. While the public often views Zero-Knowledge tech through the lens of retail scaling, Alex is quietly reshaping the bedrock of global banking. Matter Labs has launched a massive institutional play: partnering with BitGo and the Cari Network—a powerhouse banking initiative led by former U.S. Comptroller of the Currency Gene Ludwig and backed by regional giants holding over $600 billion in deposits. Using ZKsync’s enterprise-grade Prividium infrastructure, they are bringing private, always-on tokenized deposits directly onto bank balance sheets. Today, we are breaking down the closed-door banking conversations, Wall Street&apos;s pushback against the Clarity Act, and why tokenized deposits and stablecoins aren&apos;t fighting a turf war, but are actually building the future of money together. Let’s dive in. Send us Fan Mail Many more amazing technology episodes to come! Subscribe and prepare for the new world. If you would like to join the show, please reach out. For more information, please visit the following: Website: https://www.josephraczynski.com/ Blog: https://JTConsultingMedia.com/ Podcast: https://techsnippetstoday.buzzsprout.com LinkedIn: https://www.linkedin.com/in/joerazz/ X: https://x.com/joerazz"
    }
  ],
  "stats": {
    "podcastEpisodes": 3
  }
}